{
    "2023": {
        "posts": [
            {
                "title": "CodeForces XOR problem",
                "pageID": 0,
                "published": 20230916,
                "updated": 20231204,
                "mainImg": "images/activity/20230916_CodeForces_XOR_1.png",
                "summary": "Detailed explanation of problem 1847C (with XOR)",
                "contentLink": "20230916_CodeForces_XOR.md"
            },
            {
                "title": "2023 Halloween Costume Log",
                "pageID": 1,
                "published": 20230926,
                "updated": 20231021,
                "mainImg": "images/activity/20230926_halloween_2023_4.jpg",
                "summary": "Photos, sketches, descriptions. Your favorite demon from the Nightmare Realm.",
                "contentLink": "20230926_Halloween_Costume.md"
            }
        ]
    },
    "2024": {
        "posts": [
            {
                "title": "Deriving Maxwell's Equations - Notes",
                "pageID": 2,
                "published": 20240114,
                "updated": 20240922,
                "mainImg": "images/activity/20240114_maxwells_equations_1.png",
                "summary": "Math final project - deriving the 4 equations with multivariable calc.",
                "contentLink": "20240114_Maxwells_Equations.md"
            },
            {
                "title": "Sublime Text Package Configuration",
                "pageID": 4,
                "published": 20240201,
                "updated": 20240923,
                "mainImg": "images/activity/20240201_Nord_Theme_3.png",
                "summary": "Installation of Terminus and Nord theme.",
                "contentLink": "20240201_Sublime_Text_Package_Config.md"
            },
            {
                "title": "Submissions for BallsDex Art Contest",
                "pageID": 5,
                "published": 20240407,
                "updated": 20240418,
                "mainImg": "images/activity/20240407_BallsDex_Contest_6.png",
                "summary": "Mongol Empire and Polish-Lithuanian Commonwealth",
                "contentLink": "20240407_BallsDex_Art_Contest.md"
            },
            {
                "title": "2024 Summer of Greek (Classical Edition)",
                "pageID": 6,
                "mainImg": "images/activity/20240708_AlphaToOmega.jpg",
                "published": 20240708,
                "updated": 20240708,
                "summary": "Let's see how this goes.<br>EDIT: Welp, gonna have to extend this.",
                "contentLink": "20240708_Summer_Of_Greek.md"
            },
            {
                "title": "2024 Halloween Costume Log",
                "pageID": 7,
                "mainImg": "images/activity/20241016_halloween_2024_7.jpg",
                "published": 20241016,
                "updated": 20241126,
                "summary": "Happy Halloween from the Grim Proctor",
                "contentLink": "20241016_Halloween_Costume.md"
            },
            {
                "title": "Polytonic Greek for LaTeX",
                "pageID": 8,
                "mainImg": "images/activity/20241108_Polytonic_Greek_Setup_3.png",
                "published": 20241108,
                "updated": 20241108,
                "summary": "Tidy Greek with macron and accent combinations",
                "contentLink": "20241108_Polytonic_Greek_Setup.md"
            },
            {
                "title": "Simple Interference Pattern",
                "pageID": 9,
                "mainImg": "images/activity/20241223_Interference_Bands_3.png",
                "published": 20241223,
                "updated": 20241224,
                "summary": "Basic double slit stuff with two laser pointers. The calculations worked out surprisingly well.",
                "contentLink": "20241223_Interference_Bands.md"
            },
            {
                "title": "My florr.io Builds",
                "pageID": 10,
                "mainImg": "images/activity/20241226_florr_builds_3.png",
                "published": 20241226,
                "updated": 20241226,
                "summary": "Collection of the loadouts I use + explanations for usage",
                "contentLink": "20241226_Florr_Builds.md"
            },
            {
                "title": "2024: Year in Review",
                "pageID": 11,
                "mainImg": null,
                "published": 20241227,
                "updated": 20250102,
                "summary": "Goodbye 2024",
                "contentLink": "20241227_Year_Review.md"
            }
        ]
    },
    "2025": {
        "posts": [
            {
                "title": "Fibonacci Sequence Closed Form",
                "pageID": 12,
                "mainImg": "images/activity/20250103_closed_fibonacci.jpg",
                "published": 20250102,
                "updated": 20250102,
                "summary": "Deriving the closed-form Fibonacci sequence with linear algebra techniques",
                "contentLink": "20250102_Fibonacci_Closed_Form.md"
            },
            {
                "title": "Greek Tenses: Time vs Aspect",
                "pageID": 13,
                "mainImg": "images/activity/20250104_time_aspect.jpg",
                "published": 20250104,
                "updated": 20250104,
                "summary": "The distinction and why you should care (spoiler: you shouldn't).",
                "contentLink": "20250104_Time_vs_Aspect.md"
            },
            {
                "title": "Mimicking Live Data on Static Sites",
                "pageID": 14,
                "published": 20250111,
                "updated": 20250111,
                "mainImg": "images/activity/20250111_fake_api_1.png",
                "summary": "Why did I spend a week doing this",
                "contentLink": "20250111_Fake_API.md"
            },
            {
                "title": "Geometry of Spacetime I: Minkowski Diagrams",
                "pageID": 15,
                "published": 20250204,
                "updated": 20250206,
                "mainImg": "/images/activity/20250204_geometry_of_spacetime_8.png",
                "summary": "Part 1: Minkowski diagrams, causal diamonds, geometric metric derivation.",
                "contentLink": "20250204_Geometry_of_Spacetime_1.md"
            },
            {
                "title": "Geometry of Spacetime II: Kinematical Effects",
                "pageID": 16,
                "published": 20250205,
                "updated": 20250205,
                "mainImg": "/images/activity/20250205_geometry_of_spacetime_1.png",
                "summary": "Part 2: Time dilation, length contraction, and the twin paradox.",
                "contentLink": "20250205_Geometry_of_Spacetime_2.md"
            },
            {
                "title": "Geometry of Spacetime III: More Math",
                "pageID": 17,
                "published": 20250207,
                "updated": 20250207,
                "mainImg": "/images/activity/20250207_geometry_of_spacetime_1.png",
                "summary": "Part 3: Lorentz transformations, the Poincaré group, and topology.",
                "contentLink": "20250207_Geometry_of_Spacetime_3.md"
            },
            {
                "title": "Tuesday Meals",
                "pageID": 18,
                "published": 20250318,
                "updated": 20250318,
                "mainImg": "/images/activity/20250318_tuesday_meals_3.jpg",
                "summary": "Kiss the chef",
                "contentLink": "20250317_Tuesday_Meals.md"
            },
            {
                "title": "F=ma 2025",
                "pageID": 19,
                "published": 20250319,
                "updated": 20250319,
                "mainImg": "/images/activity/20250319_f=ma_3.png",
                "summary": "some thoughts",
                "contentLink": "20250319_F=ma_Results.md"
            },
            {
                "title": "Pics From the Nearby Park",
                "pageID": 20,
                "published": 20250507,
                "updated": 20250507,
                "mainImg": "/images/activity/20250507_grass_2.jpg",
                "summary": "very important to touch grass during finals",
                "contentLink": "20250507_Grass.md"
            }
        ]
    }
}